pydiar/__init__.py
pydiar/models/__init__.py
pydiar/models/binary_key/__init__.py
pydiar/models/binary_key/diarizationFunctions.py
pydiar/models/util.py
pydiar/util/misc.py
pydiar/util/sad.py
pydiar-0.0.7.dist-info/LICENSE
pydiar-0.0.7.dist-info/WHEEL
pydiar-0.0.7.dist-info/METADATA
pydiar-0.0.7.dist-info/RECORD
