Metadata-Version: 2.1
Name: pydiar
Version: 0.0.7
Summary: A simple to use library for speaker diarization
Home-page: https://github.com/audapolis/pydiar
License: GPL-3.0-or-later
Author: pajowu
Author-email: git@ca.pajowu.de
Requires-Python: >=3.8,<3.11
Classifier: License :: OSI Approved :: GNU General Public License v3 or later (GPLv3+)
Classifier: Programming Language :: Python :: 3
Classifier: Programming Language :: Python :: 3.8
Classifier: Programming Language :: Python :: 3.9
Requires-Dist: numpy (>=1.21.0,<2.0.0)
Requires-Dist: python_speech_features (>=0.6,<0.7)
Requires-Dist: scikit-learn (>=1.0.1,<2.0.0)
Requires-Dist: scipy (>=1.7.3,<2.0.0)
Requires-Dist: webrtcvad (>=2.0.10,<3.0.0)
Project-URL: Repository, https://github.com/audapolis/pydiar
